recaptcha_bypass/__init__.py
recaptcha_bypass/recaptcha_bypass.py
recaptcha_bypass-0.2.dist-info/METADATA
recaptcha_bypass-0.2.dist-info/WHEEL
recaptcha_bypass-0.2.dist-info/top_level.txt
recaptcha_bypass-0.2.dist-info/RECORD
